LICENSE
MANIFEST.in
README.md
setup.py
emoji_unicode/__init__.py
emoji_unicode/__init__.pyc
emoji_unicode/data_parser.py
emoji_unicode/data_parser.pyc
emoji_unicode/emoji-data.txt
emoji_unicode/models.py
emoji_unicode/models.pyc
emoji_unicode/parser.py
emoji_unicode/parser.pyc
emoji_unicode/pattern.py
emoji_unicode/pattern.pyc
emoji_unicode/pattern_template.py
emoji_unicode/utils.py
emoji_unicode/utils.pyc
emoji_unicode.egg-info/PKG-INFO
emoji_unicode.egg-info/SOURCES.txt
emoji_unicode.egg-info/dependency_links.txt
emoji_unicode.egg-info/not-zip-safe
emoji_unicode.egg-info/top_level.txt
emoji_unicode/__pycache__/__init__.cpython-35.pyc
emoji_unicode/__pycache__/__init__.cpython-36.pyc
emoji_unicode/__pycache__/data_parser.cpython-35.pyc
emoji_unicode/__pycache__/data_parser.cpython-36.pyc
emoji_unicode/__pycache__/models.cpython-35.pyc
emoji_unicode/__pycache__/models.cpython-36.pyc
emoji_unicode/__pycache__/parser.cpython-35.pyc
emoji_unicode/__pycache__/parser.cpython-36.pyc
emoji_unicode/__pycache__/pattern.cpython-35.pyc
emoji_unicode/__pycache__/pattern.cpython-36.pyc
emoji_unicode/__pycache__/utils.cpython-35.pyc
emoji_unicode/__pycache__/utils.cpython-36.pyc
tests/__init__.py
tests/tests.py